cipherface/__init__.py
cipherface/commons/__init__.py
cipherface/commons/file_utils.py
cipherface/commons/logger.py
cipherface/commons/phe_utils.py
cipherface/interfaces/CipherFaceInterface.py
cipherface/interfaces/__init__.py
cipherface-0.0.2.data/data/README.md
cipherface-0.0.2.data/data/requirements.txt
cipherface-0.0.2.dist-info/LICENSE
cipherface-0.0.2.dist-info/METADATA
cipherface-0.0.2.dist-info/WHEEL
cipherface-0.0.2.dist-info/top_level.txt
cipherface-0.0.2.dist-info/RECORD
