Metadata-Version: 2.1
Name: cipherface
Version: 0.0.2
Summary: A Homomorphic Encryption-Driven Framework for Secure Cloud-Based Facial Recognition
Home-page: https://github.com/serengil/cipherface
Author: Sefik Ilkin Serengil
Author-email: serengil@gmail.com
License: MIT
Platform: UNKNOWN
Classifier: Programming Language :: Python :: 3
Classifier: License :: OSI Approved :: MIT License
Classifier: Operating System :: OS Independent
Requires-Python: >=3.7
License-File: LICENSE
Requires-Dist: numpy
Requires-Dist: deepface
Requires-Dist: tenseal (==0.3.6)
Requires-Dist: tqdm
Requires-Dist: lightphe
